{
  "buildNumber": "126447",
  "versionTs": "1782244971",
  "versionHash": "a962cd0571bb6cb03ab92eb0dedb1cab8098c213",
  "cdnBase": "https://a.slack-edge.com/bv1-13-br/",
  "capturedDate": "2026-06-23",
  "manifestChunks": 1415,
  "minedChunks": 1415,
  "failedChunks": 12,
  "failedChunkFiles": [
    "gantry-v2.0f521f20cb77abe6e425.min.js",
    "gantry-v2.18be654031f1305512c7.min.js",
    "gantry-v2.2d9311419c3c61a8f6aa.min.js",
    "gantry-v2.4ff5f20a17bf2f362875.min.js",
    "gantry-v2.5df09153c99bbcab131e.min.js",
    "gantry-v2.85fa6131a35d5ff0b6ba.min.js",
    "gantry-v2.afa222dc3b3ca68b0a1d.min.js",
    "gantry-v2.b28f5754741565de786e.min.js",
    "gantry-v2.c55da1cd245c36c7fc9e.min.js",
    "gantry-v2.ecfccc041085a583a74b.min.js",
    "gantry-v2.fd24dcda401ebd414882.min.js",
    "gantry-v2.ff47a9322fa94c0bc7bc.min.js"
  ],
  "counts": {
    "apiMethods": 1713,
    "apiArgs": 583,
    "featureFlags": 278,
    "experiments": 105,
    "errorCodes": 735,
    "slashCommands": 290,
    "oauthScopes": 72,
    "analyticsEvents": 404,
    "workflowFunctions": 73,
    "workflowEvents": 25,
    "notificationTypes": 32,
    "aiFeatures": 21,
    "mcpActions": 11,
    "blockKitTypes": 83,
    "traceSpans": 79,
    "iconNames": 253,
    "keyboardShortcuts": 14,
    "devCommands": 24,
    "uiStrings": 25638
  }
}
