{
  "buildNumber": "126004",
  "versionTs": "1781553767",
  "versionHash": "1ae9268c6546cd002c66bea39720f4cebfbfd1d9",
  "cdnBase": "https://a.slack-edge.com/bv1-13-br/",
  "capturedDate": "2026-06-15",
  "manifestChunks": 1392,
  "minedChunks": 1392,
  "failedChunks": 12,
  "failedChunkFiles": [
    "gantry-v2.34ce627c19281e30d817.min.js",
    "gantry-v2.45b05386cbc1500b9f8e.min.js",
    "gantry-v2.4e90dc225eec9ed4fb87.min.js",
    "gantry-v2.5346dbcc94d64b984e70.min.js",
    "gantry-v2.7b32f444df2843ec4695.min.js",
    "gantry-v2.c2b597eeca3059e06242.min.js",
    "gantry-v2.c5dd71bf13ac5691a21a.min.js",
    "gantry-v2.cdb95ce441f2b77e4cc3.min.js",
    "gantry-v2.d97fd32bcbf026c15b6b.min.js",
    "gantry-v2.df5e6d9e098346fcc085.min.js",
    "gantry-v2.e08b471d654d3998c8e8.min.js",
    "gantry-v2.ea9a07b7a5000f7d01e6.min.js"
  ],
  "counts": {
    "apiMethods": 1689,
    "apiArgs": 583,
    "featureFlags": 274,
    "experiments": 106,
    "errorCodes": 723,
    "slashCommands": 289,
    "oauthScopes": 72,
    "analyticsEvents": 410,
    "workflowFunctions": 73,
    "workflowEvents": 25,
    "notificationTypes": 32,
    "aiFeatures": 21,
    "mcpActions": 11,
    "blockKitTypes": 83,
    "traceSpans": 78,
    "iconNames": 250,
    "keyboardShortcuts": 16,
    "devCommands": 23,
    "uiStrings": 25441
  }
}
