{
  "buildNumber": "126451",
  "versionTs": "1782248569",
  "versionHash": "13a5c9cad43ad91afe99e48bb37b92277cdea3e7",
  "cdnBase": "https://a.slack-edge.com/bv1-13-br/",
  "capturedDate": "2026-06-23",
  "manifestChunks": 1416,
  "minedChunks": 1416,
  "failedChunks": 12,
  "failedChunkFiles": [
    "gantry-v2.0eca355283ef80a67c7e.min.js",
    "gantry-v2.1807bcb505b1b28f6a63.min.js",
    "gantry-v2.25a871aadf6cba27ba9a.min.js",
    "gantry-v2.5d834cb67fbc279e8eb4.min.js",
    "gantry-v2.8a9659cd891119c74a86.min.js",
    "gantry-v2.9cd3a3741c3638999a9c.min.js",
    "gantry-v2.ac17729106a527a9e24b.min.js",
    "gantry-v2.b4e0df40e95498bd2ee1.min.js",
    "gantry-v2.bec7436985811d4c8a64.min.js",
    "gantry-v2.d0971969a9fc275240f2.min.js",
    "gantry-v2.da285c09e558bbfe31e6.min.js",
    "gantry-v2.ee210da357de5a25901d.min.js"
  ],
  "counts": {
    "apiMethods": 1715,
    "apiArgs": 583,
    "featureFlags": 280,
    "experiments": 105,
    "errorCodes": 736,
    "slashCommands": 290,
    "oauthScopes": 72,
    "analyticsEvents": 404,
    "workflowFunctions": 73,
    "workflowEvents": 25,
    "notificationTypes": 32,
    "aiFeatures": 21,
    "mcpActions": 11,
    "blockKitTypes": 83,
    "traceSpans": 79,
    "iconNames": 253,
    "keyboardShortcuts": 14,
    "devCommands": 24,
    "uiStrings": 25660
  }
}
